LAB2/problem1_seqdet/seq_detect_mealy.v

module seq_detect_mealy(
    input wire clk,
    input wire rst,
    input wire din,
    output reg y
);

// implementation of the state machine
// Define states :- 

parameter S0 = 2'b00;
parameter S1 = 2'b01;
parameter S2 = 2'b10;
parameter S3 = 2'b11;

reg[1:0] current_state,next_state;


// reset block
always @(*) begin
    if(rst)
    current_state  = S0;
    else
    current_state <=next_state;
end


//combinational logic
always @(posedge clk)begin
    next_state = current_state; // default to current state
    y = 1'b0; // default output


    case(current_state)
        S0: begin
            if(din) next_state = S1; // i/p = 1
            else next_state = S0; // i/p = 0
        end
        S1: begin
            if(din) next_state = S2; // total i/p = 11
            else next_state = S0; // total i/p = 10
        end
        S2: begin
            if(din) next_state = S2; // total i/p = 110
            else next_state = S3; // total i/p = 111
        end
        S3: begin
            if(din) begin
                y <= 1'b1; // total i/p = 1101 detected
                next_state = S1; // overlap, go back to state S1 for the next bit
            end 
            else begin
                y <= 0; // no pulse if din is not 1 after detecting 1101
                next_state = S0; // reset to state S0 if din is not 1
            end
        end
        default: begin
            next_state = S0; // default case to handle unexpected states
        end
    endcase
end


endmodule

LAB2/problem1_seqdet/tb_seq_detect_mealy.v
module tb_seq_detect_mealy;
    reg clk;
    reg rst;
    reg din;
    wire y;

    // Instantiate the DUT (Device Under Test)
    seq_detect_mealy dut(
        .clk(clk),
        .rst(rst),
        .din(din),
        .y(y)
    );

    // Clock generation
    initial begin
        clk = 0;
        forever #5 clk = ~clk; // 100 MHz clock
    end

    // Test sequence
    initial begin
        // Initialize signals
        rst = 1;
        din = 0;
        #10 rst = 0; // Release reset

        // Drive a bitstream with overlaps
        // Example: 11011011101
        #10 din = 1; // S0 -> S1
        #10 din = 1; // S1 -> S2
        #10 din = 0; // S2 -> S3
        #10 din = 1; // S3 -> S4 (y=1)
        #10 din = 1; // S4 -> S2 (overlap)
        #10 din = 0; // S2 -> S3
        #10 din = 1; // S3 -> S4 (y=1)
        #10 din = 1; // S4 -> S2 (overlap)
        #10 din = 0; // S2 -> S3
        #10 din = 1; // S3 -> S4 (y=1)
        #10 din = 0; // S4 -> S0
        #10 din = 0; // S0 -> S0

        // Finish simulation
        #10 $finish;
    end

    // Dump waveform data
    initial begin
        $dumpfile("dump.vcd");
        $dumpvars(0, tb_seq_detect_mealy);
    end
endmodule

LAB2/problem1_seqdet/dump.vcd
$date
	Tue Aug 19 23:35:50 2025
$end
$version
	Icarus Verilog
$end
$timescale
	1s
$end
$scope module tb_seq_detect_mealy $end
$var wire 1 ! y $end
$var reg 1 " clk $end
$var reg 1 # din $end
$var reg 1 $ rst $end
$scope module dut $end
$var wire 1 " clk $end
$var wire 1 # din $end
$var wire 1 $ rst $end
$var parameter 2 % S0 $end
$var parameter 2 & S1 $end
$var parameter 2 ' S2 $end
$var parameter 2 ( S3 $end
$var reg 2 ) current_state [1:0] $end
$var reg 2 * next_state [1:0] $end
$var reg 1 ! y $end
$upscope $end
$upscope $end
$enddefinitions $end
$comment Show the parameter values. $end
$dumpall
b11 (
b10 '
b1 &
b0 %
$end
#0
$dumpvars
bx *
b0 )
1$
0#
0"
x!
$end
#5
0!
b0 *
1"
#10
0"
0$
#15
1"
#20
0"
1#
#25
b1 )
b1 *
1"
#30
0"
#35
b10 )
b10 *
1"
#40
0"
0#
#45
b11 )
b11 *
1"
#50
0"
1#
#55
b1 )
1!
b1 *
1"
#60
0"
#65
b10 )
b10 *
0!
1"
#70
0"
0#
#75
b11 )
b11 *
1"
#80
0"
1#
#85
b1 )
1!
b1 *
1"
#90
0"
#95
b10 )
b10 *
0!
1"
#100
0"
0#
#105
b11 )
b11 *
1"
#110
0"
1#
#115
b1 )
1!
b1 *
1"
#120
0"
0#
#125
b0 )
b0 *
0!
1"
