LAB2/problem3_vending/vending_mealy.v
`timescale 1ns/1ps

module vending_mealy(
  input  wire        clk,
  input  wire        rst,       // synchronous, active-high
  input  wire [1:0]  coin,      // 01=5, 10=10, 00=idle (11 ignored)
  output reg         dispense,  // 1-cycle pulse when vending
  output reg         chg5       // 1-cycle pulse when returning 5
);

  // ----------------------------------------------------------
  // State encoding (2 bits)
  // ----------------------------------------------------------
  localparam S0  = 2'd0;  // total = 0
  localparam S5  = 2'd1;  // total = 5
  localparam S10 = 2'd2;  // total = 10
  localparam S15 = 2'd3;  // total = 15

  reg [1:0] state, next;
  reg dispense_d, chg5_d;

  // ----------------------------------------------------------
  // Next-state + Mealy outputs
  // ----------------------------------------------------------
  always @(*) begin
    // defaults
    next        = state;
    dispense_d  = 1'b0;
    chg5_d      = 1'b0;

    case (state)
      // --------------------------
      S0: begin
        case (coin)
          2'b01: next = S5;    // +5
          2'b10: next = S10;   // +10
          default: next = S0;
        endcase
      end
      // --------------------------
      S5: begin
        case (coin)
          2'b01: next = S10;   // +5
          2'b10: next = S15;   // +10
          default: next = S5;
        endcase
      end
      // --------------------------
      S10: begin
        case (coin)
          2'b01: next = S15;                 // +5
          2'b10: begin                       // +10 -> vend (20)
            next       = S0;
            dispense_d = 1'b1;
            chg5_d     = 1'b0;
          end
          default: next = S10;
        endcase
      end
      // --------------------------
      S15: begin
        case (coin)
          2'b01: begin                       // +5 -> vend (20)
            next       = S0;
            dispense_d = 1'b1;
            chg5_d     = 1'b0;
          end
          2'b10: begin                       // +10 -> vend (25) + change
            next       = S0;
            dispense_d = 1'b1;
            chg5_d     = 1'b1;
          end
          default: next = S15;
        endcase
      end
      // --------------------------
      default: next = S0;
    endcase
  end

  // ----------------------------------------------------------
  // Sequential update: state + registered outputs
  // ----------------------------------------------------------
  always @(posedge clk) begin
    if (rst) begin
      state     <= S0;
      dispense  <= 1'b0;
      chg5      <= 1'b0;
    end else begin
      state     <= next;
      dispense  <= dispense_d;
      chg5      <= chg5_d;
    end
  end

endmodule

LAB2/problem3_vending/tb_vending_mealy.v
`timescale 1ns/1ps

module tb_vending_mealy;

  reg        clk;
  reg        rst;
  reg  [1:0] coin;
  wire       dispense;
  wire       chg5;

  // DUT instantiation
  vending_mealy dut (
    .clk(clk),
    .rst(rst),
    .coin(coin),
    .dispense(dispense),
    .chg5(chg5)
  );

  // Clock: 100 MHz (10 ns period)
  initial clk = 1'b0;
  always  #5 clk = ~clk;

  // Helper task
  task step(input [1:0] c);
    begin
      coin = c;
      @(posedge clk);
      $display("[%0t] coin=%b -> dispense=%0d chg5=%0d",
               $time, coin, dispense, chg5);
      coin = 2'b00; // back to idle
    end
  endtask

  // Stimulus
  initial begin
    $dumpfile("vending_mealy_tb.vcd");
    $dumpvars(0, tb_vending_mealy);

    coin = 2'b00;
    rst  = 1'b1;
    repeat (2) @(posedge clk);
    rst  = 1'b0;

    // A) 10,10 => vend
    $display("\n-- A) 10,10 -> vend --");
    step(2'b10);
    step(2'b10);

    // B) 5,5,5,5 => vend
    $display("\n-- B) 5,5,5,5 -> vend --");
    step(2'b01);
    step(2'b01);
    step(2'b01);
    step(2'b01);

    // C) 10,5,10 => vend + change
    $display("\n-- C) 10,5,10 -> vend + change --");
    step(2'b10);
    step(2'b01);
    step(2'b10);

    // D) 5,10,5 => vend
    $display("\n-- D) 5,10,5 -> vend --");
    step(2'b01);
    @(posedge clk);
    step(2'b10);
    @(posedge clk);
    step(2'b01);

    repeat (3) @(posedge clk);
    $finish;
  end

endmodule

LAB2/problem3_vending/waves/vending_mealy_tb.vcd
$date
	Tue Aug 19 15:09:40 2025
$end
$version
	Icarus Verilog
$end
$timescale
	1ps
$end
$scope module tb_vending_mealy $end
$var wire 1 ! dispense $end
$var wire 1 " chg5 $end
$var reg 1 # clk $end
$var reg 2 $ coin [1:0] $end
$var reg 1 % rst $end
$scope module dut $end
$var wire 1 # clk $end
$var wire 2 & coin [1:0] $end
$var wire 1 % rst $end
$var parameter 2 ' S0 $end
$var parameter 2 ( S10 $end
$var parameter 2 ) S15 $end
$var parameter 2 * S5 $end
$var reg 1 " chg5 $end
$var reg 1 + chg5_d $end
$var reg 1 ! dispense $end
$var reg 1 , dispense_d $end
$var reg 2 - next [1:0] $end
$var reg 2 . state [1:0] $end
$upscope $end
$scope task step $end
$var reg 2 / c [1:0] $end
$upscope $end
$upscope $end
$enddefinitions $end
$comment Show the parameter values. $end
$dumpall
b1 *
b11 )
b10 (
b0 '
$end
#0
$dumpvars
bx /
bx .
b0 -
0,
0+
b0 &
1%
b0 $
0#
x"
x!
$end
#5000
0"
0!
b0 .
1#
#10000
0#
#15000
b10 -
b10 $
b10 &
b10 /
0%
1#
#20000
0#
#25000
1,
b10 .
b0 -
b10 $
b10 &
1#
#30000
0#
#35000
1!
b0 .
0,
b1 -
b1 /
b1 $
b1 &
1#
#40000
0#
#45000
0!
b1 .
b10 -
b1 $
b1 &
1#
#50000
0#
#55000
b10 .
b11 -
b1 $
b1 &
1#
#60000
0#
#65000
1,
b11 .
b0 -
b1 $
b1 &
1#
#70000
0#
#75000
1!
b0 .
0+
0,
b10 -
b10 /
b10 $
b10 &
1#
#80000
0#
#85000
0!
b10 .
b11 -
b1 /
b1 $
b1 &
1#
#90000
0#
#95000
1+
b11 .
1,
b0 -
b10 /
b10 $
b10 &
1#
#100000
0#
#105000
1"
1!
b0 .
0+
0,
b1 -
b1 /
b1 $
b1 &
1#
#110000
0#
#115000
0"
0!
b1 .
b1 -
b0 $
b0 &
1#
#120000
0#
#125000
b11 -
b10 $
b10 &
b10 /
1#
#130000
0#
#135000
b11 .
b11 -
b0 $
b0 &
1#
#140000
0#
#145000
1,
b0 -
b1 $
b1 &
b1 /
1#
#150000
0#
#155000
1!
b0 .
0,
b0 -
b0 $
b0 &
1#
#160000
0#
#165000
0!
1#
